streamingjson/__init__.py
streamingjson/lexer.py
streamingjson/lexer_helper.py
streamingjson/lexer_tokens.py
streamingjson-0.0.5.dist-info/LICENSE
streamingjson-0.0.5.dist-info/METADATA
streamingjson-0.0.5.dist-info/WHEEL
streamingjson-0.0.5.dist-info/top_level.txt
streamingjson-0.0.5.dist-info/RECORD
