Metadata-Version: 2.1
Name: streamingjson
Version: 0.0.5
Summary: A streamlined, user-friendly JSON streaming preprocessor, crafted in Python.
Author-email: Karminski <code.karminski@outlook.com>
Project-URL: Homepage, https://github.com/karminski/streaming-json-py
Project-URL: Issues, https://github.com/karminski/streaming-json-py/issues
Classifier: Programming Language :: Python :: 3
Classifier: License :: OSI Approved :: MIT License
Classifier: Operating System :: OS Independent
Requires-Python: >=3.7
License-File: LICENSE
